pownet/__init__.py
pownet/coupler.py
pownet/data_utils.py
pownet/folder_utils.py
pownet/input.py
pownet/builder/__init__.py
pownet/builder/basebuilder.py
pownet/builder/energy_storage.py
pownet/builder/hydro.py
pownet/builder/nondispatch.py
pownet/builder/system.py
pownet/builder/thermal.py
pownet/core/__init__.py
pownet/core/data_processor.py
pownet/core/model_builder.py
pownet/core/output.py
pownet/core/record.py
pownet/core/simulation.py
pownet/core/user_constraint.py
pownet/core/visualizer.py
pownet/data_model/__init__.py
pownet/data_model/reservoir.py
pownet/database/fuels.csv
pownet/database/transmission_params.csv
pownet/optim_model/__init__.py
pownet/optim_model/model.py
pownet/optim_model/objfunc.py
pownet/optim_model/rounding_algo.py
pownet/optim_model/variable_func.py
pownet/optim_model/constraints/__init__.py
pownet/optim_model/constraints/energy_storage_constr.py
pownet/optim_model/constraints/nondispatch_constr.py
pownet/optim_model/constraints/system_constr.py
pownet/optim_model/constraints/thermal_unit_constr.py
pownet/reservoir/__init__.py
pownet/reservoir/manager.py
pownet/reservoir/reservoir.py
pownet/reservoir/reservoir_functions.py
pownet/reservoir/solve_release.py
pownet/stochastic/__init__.py
pownet/stochastic/demand.py
pownet/stochastic/kirsch_nowak.py
pownet/stochastic/solar.py
pownet/stochastic/timeseries_model.py
pownet/stochastic/timeseries_utils.py
pownet-2.3.0.dist-info/licenses/LICENSE
test_pownet/__init__.py
test_pownet/test_coupler.py
test_pownet/test_data_utils.py
test_pownet/test_folder_utils.py
test_pownet/test_model.py
test_pownet/test_builder/__init__.py
test_pownet/test_builder/test_basebuilder.py
test_pownet/test_core/__init__.py
test_pownet/test_core/test_data_processor.py
test_pownet/test_core/test_model_builder.py
test_pownet/test_data_model/__init__.py
test_pownet/test_data_model/test_reservoir.py
test_pownet/test_model_library/dummy/contract_cost.csv
test_pownet/test_model_library/dummy/demand_export.csv
test_pownet/test_model_library/dummy/hydropower.csv
pownet-2.3.0.dist-info/METADATA
pownet-2.3.0.dist-info/WHEEL
pownet-2.3.0.dist-info/top_level.txt
pownet-2.3.0.dist-info/RECORD
