Metadata-Version: 2.4
Name: pownet
Version: 2.3.0
Summary: A simple production cost model of framework for power systems
Author-email: Phumthep Bunnak <pb585@cornell.edu>
License: MIT License
Project-URL: Homepage, https://github.com/Critical-Infrastructure-Systems-Lab/PowNet
Project-URL: Documentation, https://pownet.readthedocs.io/en/latest/index.html
Keywords: power_system,optimization,production_cost_model,unit_commitment
Requires-Python: >=3.10
License-File: LICENSE
Requires-Dist: gurobipy>=11.0.3
Requires-Dist: highspy>=1.7.2
Requires-Dist: matplotlib>=3.7.1
Requires-Dist: networkx>=3.1.0
Requires-Dist: numpy>=2.2.0
Requires-Dist: pandas>=2.1.1
Requires-Dist: scipy>=1.11.3
Requires-Dist: scikit-learn>=1.5.2
Requires-Dist: statsmodels>=0.14.4
Requires-Dist: geopandas>=1.0.1
Requires-Dist: contextily>=1.6.2
Requires-Dist: coverage[toml]>=7.8.0
Requires-Dist: flake8>=7.2.0
Dynamic: license-file
